portable_python/__init__.py
portable_python/__main__.py
portable_python/cli.py
portable_python/config.py
portable_python/cpython.py
portable_python/inspector.py
portable_python/tracking.py
portable_python/versions.py
portable_python/external/__init__.py
portable_python/external/_inspect.py
portable_python/external/xcpython.py
portable_python/external/xtkinter.py
portable_python-1.10.2.dist-info/licenses/LICENSE
portable_python-1.10.2.dist-info/METADATA
portable_python-1.10.2.dist-info/WHEEL
portable_python-1.10.2.dist-info/entry_points.txt
portable_python-1.10.2.dist-info/top_level.txt
portable_python-1.10.2.dist-info/RECORD
