Metadata-Version: 2.4
Name: portable-python
Version: 1.10.2
Summary: Portable python binaries
Home-page: https://github.com/codrsquad/portable-python
Author: Zoran Simic
Author-email: zoran@simicweb.com
License: MIT
Project-URL: Documentation, https://github.com/codrsquad/portable-python/wiki
Project-URL: Release notes, https://github.com/codrsquad/portable-python/wiki/Release-notes
Project-URL: Source, https://github.com/codrsquad/portable-python
Keywords: python,portable,binary
Classifier: Development Status :: 5 - Production/Stable
Classifier: Environment :: Console
Classifier: Intended Audience :: Developers
Classifier: Operating System :: MacOS :: MacOS X
Classifier: Operating System :: POSIX
Classifier: Operating System :: Unix
Classifier: Programming Language :: Python
Classifier: Programming Language :: Python :: 3
Classifier: Programming Language :: Python :: 3.9
Classifier: Programming Language :: Python :: 3.10
Classifier: Programming Language :: Python :: 3.11
Classifier: Programming Language :: Python :: 3.12
Classifier: Programming Language :: Python :: 3.13
Classifier: Programming Language :: Python :: Implementation :: CPython
Classifier: Topic :: Software Development :: Build Tools
Classifier: Topic :: System :: Installation/Setup
Classifier: Topic :: System :: Software Distribution
Classifier: Topic :: Utilities
Requires-Python: >=3.9
License-File: LICENSE
Requires-Dist: click~=8.0
Requires-Dist: pyyaml~=6.0
Requires-Dist: requests<3.0
Requires-Dist: runez~=5.0
Requires-Dist: urllib3~=1.26
Dynamic: author
Dynamic: author-email
Dynamic: classifier
Dynamic: description
Dynamic: description-content-type
Dynamic: home-page
Dynamic: keywords
Dynamic: license
Dynamic: license-file
Dynamic: project-url
Dynamic: requires-dist
Dynamic: requires-python
Dynamic: summary
